chuck.py
setup.py
python_chuck_norris.egg-info/PKG-INFO
python_chuck_norris.egg-info/SOURCES.txt
python_chuck_norris.egg-info/dependency_links.txt
python_chuck_norris.egg-info/top_level.txt