Metadata-Version: 1.0
Name: python-chuck-norris
Version: 0.3
Summary: Chuck Norris assertions to make all your tests pass
Home-page: http://github.com/ricobl/python-chuck-norris
Author: Enrico Batista da Luz
Author-email: rico.bl@gmail.com
License: UNKNOWN
Platform: UNKNOWN
